minicfg-3.0.2.dist-info/METADATA
minicfg-3.0.2.dist-info/WHEEL
minicfg-3.0.2.dist-info/entry_points.txt
minicfg-3.0.2.dist-info/licenses/LICENSE
minicfg/__init__.py
minicfg/__main__.py
minicfg/caster.py
minicfg/docs_generator.py
minicfg/field.py
minicfg/minicfg.py
minicfg/provider.py
minicfg-3.0.2.dist-info/RECORD
