Metadata-Version: 2.1
Name: minicfg
Version: 3.0.2
Summary: minicfg is a lightweight, minimalistic and easy-to-use configuration package for your Python services.
Author-Email: jieggii <jieggii@protonmail.com>
License: MIT
Requires-Python: >=3.9
